README.md
setup.py
replapi2/__init__.py
replapi2/main.py
replapi2.egg-info/PKG-INFO
replapi2.egg-info/SOURCES.txt
replapi2.egg-info/dependency_links.txt
replapi2.egg-info/requires.txt
replapi2.egg-info/top_level.txt
replapi2.egg-info/zip-safe