Metadata-Version: 2.1
Name: replapi2
Version: 0.0.1
Summary: replapi2 (replit.com api) by ch1ck3n
Home-page: https://replit.com/@ch1ck3n/replapi-v2
Author: ch1ck3n
Author-email: chcknch1ck3n@gmail.com
License: MIT
Platform: UNKNOWN
Classifier: Programming Language :: Python :: 3
Classifier: License :: OSI Approved :: GNU General Public License v3 (GPLv3)
Classifier: Operating System :: OS Independent
Requires-Python: >=3.0
